pytest_impacted/__init__.py
pytest_impacted/api.py
pytest_impacted/cli.py
pytest_impacted/display.py
pytest_impacted/git.py
pytest_impacted/graph.py
pytest_impacted/parsing.py
pytest_impacted/plugin.py
pytest_impacted/strategies.py
pytest_impacted/traversal.py
pytest_impacted-0.14.0.dist-info/licenses/LICENSE
pytest_impacted-0.14.0.dist-info/METADATA
pytest_impacted-0.14.0.dist-info/WHEEL
pytest_impacted-0.14.0.dist-info/entry_points.txt
pytest_impacted-0.14.0.dist-info/top_level.txt
pytest_impacted-0.14.0.dist-info/RECORD
