Metadata-Version: 2.4
Name: pytest-impacted
Version: 0.14.0
Summary: A pytest plugin that selectively runs tests impacted by codechanges via git introspection, ASL parsing, and dependency graph analysis.
Author-email: PromptRomp <promptromp.contact@gmail.com>
Maintainer-email: PromptRomp <promptromp.contact@gmail.com>
License-Expression: MIT
Project-URL: Homepage, https://github.com/promptromp/pytest-impacted
Project-URL: Issues, https://github.com/promptromp/pytest-impacted/issues
Classifier: Framework :: Pytest
Classifier: Development Status :: 4 - Beta
Classifier: Intended Audience :: Developers
Classifier: Topic :: Software Development :: Testing
Classifier: Operating System :: OS Independent
Classifier: Programming Language :: Python
Classifier: Programming Language :: Python :: 3.11
Classifier: Programming Language :: Python :: 3.12
Classifier: Programming Language :: Python :: 3.13
Classifier: Programming Language :: Python :: 3 :: Only
Classifier: Programming Language :: Python :: Implementation :: CPython
Classifier: Programming Language :: Python :: Implementation :: PyPy
Requires-Python: >=3.11
License-File: LICENSE
Requires-Dist: astroid>=3.3.10
Requires-Dist: click>=8.2.0
Requires-Dist: gitpython>=3.1.44
Requires-Dist: networkx>=3.4.2
Requires-Dist: pytest>=8.0.0
Requires-Dist: rich>=14.0.0
Dynamic: license-file
